kenobi.py
data/__init__.py
helpers/__init__.py
helpers/custom_logger.py
helpers/emulator.py
helpers/local_ip.py
helpers/message_parser.py
helpers/operating_system.py
helpers/websocket_server.py
test/__init__.py
test/test_os.py
test/test_parser.py
kenobi_app-2022.1.2.dist-info/LICENSE.md
kenobi_app-2022.1.2.dist-info/METADATA
kenobi_app-2022.1.2.dist-info/WHEEL
kenobi_app-2022.1.2.dist-info/top_level.txt
kenobi_app-2022.1.2.dist-info/RECORD
