Metadata-Version: 2.1
Name: kenobi-app
Version: 2022.1.2
Summary: Opensource desktop application for Kenobi
Home-page: https://github.com/Aayush9029/Kenobi-Server/tree/main
Author: Aayush Pokharel
Author-email: aayushpokharel36@gmail.com
License: UNKNOWN
Platform: UNKNOWN
Classifier: Programming Language :: Python
Classifier: Programming Language :: Python :: 3
Classifier: Programming Language :: Python :: 3.6
Classifier: Programming Language :: Python :: 3.7
Classifier: Programming Language :: Python :: 3.8
Classifier: License :: OSI Approved :: MIT License
Classifier: Operating System :: OS Independent
Requires: websockets
Requires: pynput
Requires: playsound
License-File: LICENSE.md
Requires-Dist: websockets
Requires-Dist: pynput
Requires-Dist: playsound
